common/Response.py
common/__init__.py
wrapper/__init__.py
wrapper/mcp_wrapper.py
weather001-0.1.1.dist-info/METADATA
weather001-0.1.1.dist-info/WHEEL
weather001-0.1.1.dist-info/entry_points.txt
weather001-0.1.1.dist-info/top_level.txt
weather001-0.1.1.dist-info/RECORD
