Metadata-Version: 2.4
Name: weather001
Version: 0.1.1
Summary: A weather application using MCP
Author-email: Your Name <your.email@example.com>
License: MIT
Classifier: Development Status :: 3 - Alpha
Classifier: Intended Audience :: Developers
Classifier: License :: OSI Approved :: MIT License
Classifier: Programming Language :: Python :: 3
Classifier: Programming Language :: Python :: 3.8
Classifier: Programming Language :: Python :: 3.9
Classifier: Programming Language :: Python :: 3.10
Classifier: Programming Language :: Python :: 3.11
Requires-Python: >=3.8
Requires-Dist: requests>=2.31.0
Requires-Dist: python-dotenv>=1.0.0
Requires-Dist: fastmcp>=2.0.0
